odoo/addons/payroll_hr_public_holidays/README.rst
odoo/addons/payroll_hr_public_holidays/__init__.py
odoo/addons/payroll_hr_public_holidays/__manifest__.py
odoo/addons/payroll_hr_public_holidays/i18n/es_AR.po
odoo/addons/payroll_hr_public_holidays/i18n/payroll_hr_public_holidays.pot
odoo/addons/payroll_hr_public_holidays/models/__init__.py
odoo/addons/payroll_hr_public_holidays/models/hr_payslip.py
odoo/addons/payroll_hr_public_holidays/readme/CONTRIBUTORS.rst
odoo/addons/payroll_hr_public_holidays/readme/DESCRIPTION.rst
odoo/addons/payroll_hr_public_holidays/readme/USAGE.rst
odoo/addons/payroll_hr_public_holidays/static/description/icon.png
odoo/addons/payroll_hr_public_holidays/static/description/index.html
odoo14_addon_payroll_hr_public_holidays-14.0.2.0.0.dist-info/METADATA
odoo14_addon_payroll_hr_public_holidays-14.0.2.0.0.dist-info/WHEEL
odoo14_addon_payroll_hr_public_holidays-14.0.2.0.0.dist-info/top_level.txt
odoo14_addon_payroll_hr_public_holidays-14.0.2.0.0.dist-info/RECORD
